LICENSE
MANIFEST.in
README.md
requirements.txt
setup.py
src/pii_extract/__init__.py
src/pii_extract/piientity.py
src/pii_extract/piienum.py
src/pii_extract.egg-info/PKG-INFO
src/pii_extract.egg-info/SOURCES.txt
src/pii_extract.egg-info/dependency_links.txt
src/pii_extract.egg-info/entry_points.txt
src/pii_extract.egg-info/requires.txt
src/pii_extract.egg-info/top_level.txt
src/pii_extract/api/__init__.py
src/pii_extract/api/file.py
src/pii_extract/api/finder.py
src/pii_extract/app/__init__.py
src/pii_extract/app/address.py
src/pii_extract/app/evaluator.py
src/pii_extract/app/extract.py
src/pii_extract/app/task_info.py
src/pii_extract/helper/__init__.py
src/pii_extract/helper/base.py
src/pii_extract/helper/context.py
src/pii_extract/helper/exception.py
src/pii_extract/helper/json.py
src/pii_extract/helper/normalizer.py
src/pii_extract/helper/plugins.py
src/pii_extract/helper/taskdict.py
src/pii_extract/helper/types.py
src/pii_extract/helper/tasks/__init__.py
src/pii_extract/lang/__init__.py
src/pii_extract/lang/any/__init__.py
src/pii_extract/lang/any/bitcoin_address.py
src/pii_extract/lang/any/credit_card.py
src/pii_extract/lang/any/email.py
src/pii_extract/lang/any/ip_address.py
src/pii_extract/lang/en/__init__.py
src/pii_extract/lang/en/any/__init__.py
src/pii_extract/lang/en/any/international_phone_number.py
src/pii_extract/lang/en/au/__init__.py
src/pii_extract/lang/en/au/abn.py
src/pii_extract/lang/en/au/tfn.py
src/pii_extract/lang/en/ca/__init__.py
src/pii_extract/lang/en/ca/social_insurance_number.py
src/pii_extract/lang/en/in_/__init__.py
src/pii_extract/lang/en/in_/aadhaar.py
src/pii_extract/lang/en/us/__init__.py
src/pii_extract/lang/en/us/social_security_number.py
src/pii_extract/lang/es/__init__.py
src/pii_extract/lang/es/any/__init__.py
src/pii_extract/lang/es/any/international_phone_number.py
src/pii_extract/lang/es/es/__init__.py
src/pii_extract/lang/es/es/bank_account.py
src/pii_extract/lang/es/es/govid.py
src/pii_extract/lang/es/mx/__init__.py
src/pii_extract/lang/es/mx/curp.py
src/pii_extract/lang/fr/__init__.py
src/pii_extract/lang/fr/ca/__init__.py
src/pii_extract/lang/fr/ca/social_insurance_number.py
src/pii_extract/lang/pt/__init__.py
src/pii_extract/lang/pt/br/__init__.py
